bra_scraper/BRA.py
bra_scraper/__init__.py
bra_scraper/category.py
bra_scraper/dimension.py
bra_scraper/interface.py
bra_scraper/note.py
bra_scraper/resultset.py
bra_scraper/surfer.py
bra_scraper/topic.py
bra_scraper/utils.py
bra_scraper-0.2.4.dist-info/METADATA
bra_scraper-0.2.4.dist-info/WHEEL
bra_scraper-0.2.4.dist-info/top_level.txt
bra_scraper-0.2.4.dist-info/RECORD
