Metadata-Version: 2.1
Name: bra-scraper
Version: 0.2.4
Summary: An interface for fetching statistical data from BRÅ. This is not an official service!
Home-page: https://github.com/jensfinnas/bra_scraper
Author: Jens Finnäs
Author-email: jens.finnas@gmail.com
License: MIT
Platform: UNKNOWN
Requires-Dist: lxml (>=4.6.2)
Requires-Dist: python-dateutil (>=2.8.1)
Requires-Dist: requests (>=2.11.1)
